mseep_roblox_mcp-0.1.1.dist-info/licenses/LICENSE
roblox_mcp/__init__.py
roblox_mcp/config.py
roblox_mcp/roblox_client.py
roblox_mcp/server.py
roblox_mcp/sse.py
mseep_roblox_mcp-0.1.1.dist-info/METADATA
mseep_roblox_mcp-0.1.1.dist-info/WHEEL
mseep_roblox_mcp-0.1.1.dist-info/entry_points.txt
mseep_roblox_mcp-0.1.1.dist-info/top_level.txt
mseep_roblox_mcp-0.1.1.dist-info/RECORD
